{
  "collected_at": "2026-04-04T16:22:22.644055+00:00",
  "source": "discord",
  "item_count": 6,
  "items": [
    {
      "source": "discord",
      "time": "2026-04-04T14:05:20.324258+00:00",
      "lang": "",
      "title": "Discord 社区日报 (2026-04-04)",
      "summary": "今日 2,469 条消息，192 位活跃用户，201 次反应。热门频道：🔸綜合討論(571)、🔸game-question(493)、🔸phòng-chat-tiếng-việt(477)、🔸general-chat(387)、🔸한국어-채팅방(147)",
      "url": "",
      "author": "Discord Archiver",
      "engagement": 2469
    },
    {
      "source": "discord",
      "time": "2026-04-04T14:05:20.324273+00:00",
      "lang": "",
      "title": "Discord官方通知：英语语言设置异常",
      "summary": "官方发布通知，确认部分更新后安装客户端的守望者遇到英语语言设置失效问题，正在修复中。",
      "url": "",
      "author": "morimensstaff02",
      "engagement": 10
    },
    {
      "source": "discord",
      "time": "2026-04-04T14:05:20.324277+00:00",
      "lang": "",
      "title": "[DC热门] sunstopshining@William says lock in:",
      "summary": "",
      "url": "",
      "author": "sunstopshining",
      "engagement": 8
    },
    {
      "source": "discord",
      "time": "2026-04-04T14:05:20.324280+00:00",
      "lang": "",
      "title": "[DC热门] water_heart@🔸綜合討論:",
      "summary": "",
      "url": "",
      "author": "water_heart",
      "engagement": 5
    },
    {
      "source": "discord",
      "time": "2026-04-04T14:05:20.324282+00:00",
      "lang": "",
      "title": "[DC热门] calvin_hz@🔸綜合討論: 玩了 大概12天",
      "summary": "玩了 大概12天",
      "url": "",
      "author": "calvin_hz",
      "engagement": 5
    },
    {
      "source": "discord",
      "time": "2026-04-04T14:05:20.324285+00:00",
      "lang": "",
      "title": "[DC热门] salami_87@🔸canal-español:",
      "summary": "",
      "url": "",
      "author": "salami_87",
      "engagement": 5
    }
  ]
}